LICENSE
MANIFEST.in
README.md
setup.py
django_discord_connector/__init__.py
django_discord_connector/admin.py
django_discord_connector/apps.py
django_discord_connector/bindings.py
django_discord_connector/forms.py
django_discord_connector/models.py
django_discord_connector/request.py
django_discord_connector/signals.py
django_discord_connector/tasks.py
django_discord_connector/urls.py
django_discord_connector/views.py
django_discord_connector.egg-info/PKG-INFO
django_discord_connector.egg-info/SOURCES.txt
django_discord_connector.egg-info/dependency_links.txt
django_discord_connector.egg-info/requires.txt
django_discord_connector.egg-info/top_level.txt
django_discord_connector/fixtures/discord_default_schedule.json
django_discord_connector/migrations/0001_initial.py
django_discord_connector/migrations/0002_auto_20190823_1722.py
django_discord_connector/migrations/0003_discordclient_invite_link.py
django_discord_connector/migrations/0004_auto_20190826_1348.py
django_discord_connector/migrations/0005_auto_20190904_1643.py
django_discord_connector/migrations/0006_auto_20190918_1914.py
django_discord_connector/migrations/0007_auto_20191118_1402.py
django_discord_connector/migrations/0008_auto_20200107_1431.py
django_discord_connector/migrations/0009_auto_20200929_2007.py
django_discord_connector/migrations/0010_auto_20201120_2152.py
django_discord_connector/migrations/__init__.py
django_discord_connector/tests/__init__.py
django_discord_connector/tests/test_models.py
django_discord_connector/tests/test_signals.py
django_discord_connector/tests/test_tasks.py
django_discord_connector/tests/test_views.py