Metadata-Version: 2.1
Name: django-discord-connector
Version: 1.2.1
Summary: A simple Django application that adds Discord entities and SSO handling
Home-page: https://github.com/KryptedGaming/django-discord-connector
Author: porowns
Author-email: porowns@gmail.com
License: MIT License
Platform: UNKNOWN
Classifier: Environment :: Web Environment
Classifier: Framework :: Django
Classifier: Intended Audience :: Developers
Classifier: License :: OSI Approved :: MIT License
Classifier: Operating System :: OS Independent
Classifier: Programming Language :: Python
Classifier: Programming Language :: Python :: 3.5
Classifier: Programming Language :: Python :: 3.6
Classifier: Topic :: Internet :: WWW/HTTP
Classifier: Topic :: Internet :: WWW/HTTP :: Dynamic Content
